LICENSE
MANIFEST.in
Makefile
README
setup.py
pyrg/pyrg.py
pyrg/pyrg.egg-info/PKG-INFO
pyrg/pyrg.egg-info/SOURCES.txt
pyrg/pyrg.egg-info/dependency_links.txt
pyrg/pyrg.egg-info/entry_points.txt
pyrg/pyrg.egg-info/not-zip-safe
pyrg/pyrg.egg-info/top_level.txt
test/testall.py