Metadata-Version: 1.0
Name: pyrg
Version: 0.2.1
Summary: Python UnitTest Result colorized
Home-page: http://www.hexacosa.net/project/pyrg/
Author: Hideo Hattori
Author-email: hhatto.jp@gmail.com
License: New BSD License
Keywords: unittest colorize visualize
Platform: UNKNOWN
Classifier: Development Status :: 3 - Alpha
Classifier: Intended Audience :: Developers
Classifier: Environment :: Console
Classifier: Operating System :: Unix
Classifier: License :: OSI Approved :: BSD License
Classifier: Programming Language :: Python
Classifier: Topic :: Software Development
Classifier: Topic :: Software Development :: Testing
